Metadata-Version: 2.1
Name: openshift-python-wrapper-data-collector
Version: 1.0.4
Summary: Data collector for https://github.com/openshift/openshift-python-wrapper when running with PyTest
Home-page: https://github.com/RedHatQE/openshift-python-wrapper-data-collector
Download-URL: https://github.com/RedHatQE/openshift-python-wrapper-data-collector/archive/refs/tags/1.0.4.tar.gz
Author: Meni Yakove, Ruth Netser
Author-email: rnetser@redhat.com, myakove@redhat.com
License: apache-2.0
Project-URL: Bug Tracker, https://github.com/RedHatQE/openshift-python-wrapper-data-collector/issues
Keywords: Openshift
Classifier: Programming Language :: Python :: 3
Classifier: Operating System :: OS Independent
Requires-Python: >=3.8
License-File: LICENSE
